refcontainer/__init__.py
refcontainer/reference_container.py
refcontainer/strong_generic.py
refcontainer-0.0.3.dist-info/METADATA
refcontainer-0.0.3.dist-info/WHEEL
refcontainer-0.0.3.dist-info/licenses/LICENSE
refcontainer-0.0.3.dist-info/RECORD
