Metadata-Version: 2.1
Name: refcontainer
Version: 0.0.3
Summary: A fully typed Ref(...) object to reference a value, with runtime typechecking.
Project-URL: Homepage, https://github.com/balintmaci/python-ref
Project-URL: Bug Tracker, https://github.com/balintmaci/python-ref/issues
Author: Balint Barna Kovari
License: MIT License
Classifier: License :: OSI Approved :: MIT License
Classifier: Operating System :: OS Independent
Classifier: Programming Language :: Python :: 3
Requires-Python: >=3.8
